Metadata-Version: 2.1
Name: odoo14-addon-shopfloor-single-product-transfer-force-package
Version: 14.0.1.2.0
Summary: Force to select package if location already contains packages.
Home-page: https://github.com/OCA/wms
Author: Camptocamp, Odoo Community Association (OCA)
Author-email: support@odoo-community.org
License: AGPL-3
Platform: UNKNOWN
Classifier: Programming Language :: Python
Classifier: Framework :: Odoo
Classifier: Framework :: Odoo :: 14.0
Classifier: License :: OSI Approved :: GNU Affero General Public License v3
Requires-Python: >=3.6
Requires-Dist: odoo14-addon-shopfloor
Requires-Dist: odoo14-addon-shopfloor-single-product-transfer
Requires-Dist: odoo14-addon-stock-location-package-restriction
Requires-Dist: odoo <14.1dev,>=14.0a
